checker/__init__.py
checker/__main__.py
checker/app.py
checker/backend.py
checker/const.py
checker/gui.py
checker/logger.py
checker/backends/__init__.py
checker/backends/arch_cgit.py
checker/backends/bitbucket.py
checker/backends/cpan.py
checker/backends/custom.py
checker/backends/debian_cgit.py
checker/backends/debian_ftp.py
checker/backends/gentoo_cgit.py
checker/backends/github.py
checker/backends/gnome.py
checker/backends/gnu.py
checker/backends/jetbrains.py
checker/backends/launchpad.py
checker/backends/maven.py
checker/backends/npmjs.py
checker/backends/nvidia.py
checker/backends/opera.py
checker/backends/packagist.py
checker/backends/pagure.py
checker/backends/pypi.py
checker/backends/qt_ftp.py
checker/backends/rubygems.py
checker/backends/sourceforge.py
checker/backends/wps.py
checker/locale/zh_CN.qm
checker/locale/zh_TW.qm
repo_checker-0.2.0.dist-info/DESCRIPTION.rst
repo_checker-0.2.0.dist-info/LICENSE.txt
repo_checker-0.2.0.dist-info/METADATA
repo_checker-0.2.0.dist-info/RECORD
repo_checker-0.2.0.dist-info/WHEEL
repo_checker-0.2.0.dist-info/entry_points.txt
repo_checker-0.2.0.dist-info/metadata.json
repo_checker-0.2.0.dist-info/top_level.txt
