Metadata-Version: 2.0
Name: repo-checker
Version: 0.2.0
Summary: A graphical user interface version checker for open source project.
Home-page: https://github.com/1dot75cm/repo-checker
Author: mosquito
Author-email: sensor.wen@gmail.com
License: MIT
Keywords: network,checker,gui
Platform: any
Classifier: Development Status :: 3 - Alpha
Classifier: Environment :: Console
Classifier: Environment :: X11 Applications :: Qt
Classifier: License :: OSI Approved :: MIT License
Classifier: Natural Language :: Chinese (Simplified)
Classifier: Natural Language :: Chinese (Traditional)
Classifier: Natural Language :: English
Classifier: Operating System :: POSIX :: Linux
Classifier: Programming Language :: Python :: 2
Classifier: Programming Language :: Python :: 2.7
Classifier: Programming Language :: Python :: 3
Classifier: Programming Language :: Python :: 3.2
Classifier: Programming Language :: Python :: 3.3
Classifier: Programming Language :: Python :: 3.4
Classifier: Programming Language :: Python :: 3.5
Classifier: Programming Language :: Python :: 3.6
Classifier: Topic :: Utilities
Requires-Dist: PyQt5
Requires-Dist: requests (>=2.12.4)
Requires-Dist: lxml
Requires-Dist: python-dateutil
Requires-Dist: six
